aranizer/__init__.py
aranizer/aranizer.py
aranizer/tokenizers/bpe/BPE_tokenizer_32.0K.json
aranizer/tokenizers/bpe/BPE_tokenizer_50.0K.json
aranizer/tokenizers/bpe/BPE_tokenizer_64.0K.json
aranizer/tokenizers/bpe/BPE_tokenizer_86.0K.json
aranizer/tokenizers/bpe/TBPE_tokenizer_32.0K.json
aranizer/tokenizers/bpe/TBPE_tokenizer_50.0K.json
aranizer/tokenizers/bpe/TBPE_tokenizer_64.0K.json
aranizer/tokenizers/bpe/TBPE_tokenizer_86.0K.json
aranizer/tokenizers/sp/SP_tokenizer_32.0K.json
aranizer/tokenizers/sp/SP_tokenizer_50.0K.json
aranizer/tokenizers/sp/SP_tokenizer_64.0K.json
aranizer/tokenizers/sp/SP_tokenizer_86.0K.json
aranizer/tokenizers/sp/TSP_tokenizer_32.0K.json
aranizer/tokenizers/sp/TSP_tokenizer_50.0K.json
aranizer/tokenizers/sp/TSP_tokenizer_64.0K.json
aranizer/tokenizers/sp/TSP_tokenizer_86.0K.json
aranizer-0.2.5.dist-info/LICENSE
aranizer-0.2.5.dist-info/METADATA
aranizer-0.2.5.dist-info/WHEEL
aranizer-0.2.5.dist-info/top_level.txt
aranizer-0.2.5.dist-info/RECORD
