Metadata-Version: 2.1
Name: aranizer
Version: 0.2.5
Summary: Aranizer: A Custom Tokenizer for Enhanced Arabic Language Processing
Home-page: https://github.com/riotu-lab/aranizer
Author: RIOTU Lab
Author-email: riotu@psu.edu.sa
License: Apache 2.0
Classifier: Development Status :: 4 - Beta
Classifier: Intended Audience :: Developers
Classifier: Intended Audience :: Science/Research
Classifier: License :: OSI Approved :: Apache Software License
Classifier: Natural Language :: Arabic
Classifier: Programming Language :: Python :: 3
Classifier: Programming Language :: Python :: 3.6
Classifier: Programming Language :: Python :: 3.7
Classifier: Programming Language :: Python :: 3.8
Classifier: Programming Language :: Python :: 3.9
Classifier: Topic :: Text Processing :: Linguistic
Classifier: Topic :: Software Development :: Libraries :: Python Modules
Requires-Python: >=3.6
License-File: LICENSE
Requires-Dist: transformers >=4.0.0
Requires-Dist: sentence-transformers >=0.4.0
